LICENSE.txt
MANIFEST.in
README.md
setup.py
wifiphisher/__init__.py
wifiphisher/pywifiphisher.py
wifiphisher.egg-info/PKG-INFO
wifiphisher.egg-info/SOURCES.txt
wifiphisher.egg-info/dependency_links.txt
wifiphisher.egg-info/entry_points.txt
wifiphisher.egg-info/requires.txt
wifiphisher.egg-info/top_level.txt
wifiphisher/common/__init__.py
wifiphisher/common/accesspoint.py
wifiphisher/common/constants.py
wifiphisher/common/extensions.py
wifiphisher/common/firewall.py
wifiphisher/common/interfaces.py
wifiphisher/common/macmatcher.py
wifiphisher/common/opmode.py
wifiphisher/common/phishinghttp.py
wifiphisher/common/phishingpage.py
wifiphisher/common/recon.py
wifiphisher/common/tui.py
wifiphisher/common/uimethods.py
wifiphisher/data/wifiphisher-known-open-wlans
wifiphisher/data/wifiphisher-mac-prefixes
wifiphisher/data/cert/server.pem
wifiphisher/data/locs/.gitkeep
wifiphisher/data/phishing-pages/firmware-upgrade/config.ini
wifiphisher/data/phishing-pages/firmware-upgrade/html/bootstrap.min.css
wifiphisher/data/phishing-pages/firmware-upgrade/html/bootstrap.min.js
wifiphisher/data/phishing-pages/firmware-upgrade/html/index.html
wifiphisher/data/phishing-pages/firmware-upgrade/html/jquery.min.js
wifiphisher/data/phishing-pages/firmware-upgrade/html/loading.html
wifiphisher/data/phishing-pages/firmware-upgrade/html/upgrading.html
wifiphisher/data/phishing-pages/firmware-upgrade/html/static/bootstrap.min.css
wifiphisher/data/phishing-pages/firmware-upgrade/html/static/bootstrap.min.js
wifiphisher/data/phishing-pages/firmware-upgrade/html/static/jquery.min.js
wifiphisher/data/phishing-pages/firmware-upgrade/html/static/font-awesome-4.7.0/css/font-awesome.css
wifiphisher/data/phishing-pages/firmware-upgrade/html/static/font-awesome-4.7.0/css/font-awesome.min.css
wifiphisher/data/phishing-pages/firmware-upgrade/html/static/font-awesome-4.7.0/fonts/FontAwesome.otf
wifiphisher/data/phishing-pages/firmware-upgrade/html/static/font-awesome-4.7.0/fonts/fontawesome-webfont.eot
wifiphisher/data/phishing-pages/firmware-upgrade/html/static/font-awesome-4.7.0/fonts/fontawesome-webfont.svg
