Metadata-Version: 1.1
Name: wifiphisher
Version: 1.4
Summary: Automated phishing attacks against Wi-Fi networks
Home-page: https://github.com/wifiphisher/wifiphisher
Author: sophron
Author-email: sophron@latthi.com
License: GPL
Keywords: wifiphisher,evil,twin,phishing
Platform: UNKNOWN
Classifier: Development Status :: 5 - Production/Stable
Classifier: License :: OSI Approved :: GNU Lesser General Public License v3 (LGPLv3)
Classifier: Natural Language :: English
Classifier: Operating System :: Unix
Classifier: Programming Language :: Python :: 2
Classifier: Programming Language :: Python :: 2.7
Classifier: Programming Language :: Python :: 2 :: Only
Classifier: Topic :: Security
Classifier: Topic :: System :: Networking
Classifier: Intended Audience :: End Users/Desktop
Classifier: Intended Audience :: System Administrators
Classifier: Intended Audience :: Information Technology
